Metadata-Version: 2.1
Name: sigmoidpythonlib
Version: 0.1.0
Summary: Python Library to read file and load in Pandas DataFrames
Author: Rishabh Verma
Classifier: Programming Language :: Python :: 3
Classifier: License :: OSI Approved :: MIT License
Classifier: Operating System :: OS Independent
